CalCalc/CalCalc.py
CalCalc/__init__.py
CalCalc_jcroth-0.1.0.dist-info/LICENSE
CalCalc_jcroth-0.1.0.dist-info/METADATA
CalCalc_jcroth-0.1.0.dist-info/WHEEL
CalCalc_jcroth-0.1.0.dist-info/top_level.txt
CalCalc_jcroth-0.1.0.dist-info/RECORD
