Metadata-Version: 2.1
Name: CalCalc-jcroth
Version: 0.1.0
Summary: Evaluates mathematical expressions in strings. Also can call WolframAlpha.
Home-page: https://github.com/jc-roth/python-ay250-homework/tree/main/hw_3
Author: Jack Roth
Author-email: jack_roth@berkeley.edu
License: UNKNOWN
Platform: UNKNOWN
Requires-Python: >=3.6
License-File: LICENSE
